im2deeptrainer/__init__.py
im2deeptrainer/__main__.py
im2deeptrainer/evaluate.py
im2deeptrainer/exceptions.py
im2deeptrainer/extract_data.py
im2deeptrainer/model.py
im2deeptrainer/train.py
im2deeptrainer/utils.py
im2deeptrainer/package_data/Transfer_single_backbone.ckpt
im2deeptrainer/package_data/aa_mol_desc_feats.csv
im2deeptrainer/package_data/aa_mol_desc_feats_filtered.csv
im2deeptrainer/package_data/aa_mol_desc_feats_filtered_and_removed.csv
im2deeptrainer-0.2.2.dist-info/licenses/LICENSE
im2deeptrainer-0.2.2.dist-info/METADATA
im2deeptrainer-0.2.2.dist-info/WHEEL
im2deeptrainer-0.2.2.dist-info/entry_points.txt
im2deeptrainer-0.2.2.dist-info/top_level.txt
im2deeptrainer-0.2.2.dist-info/RECORD
