Metadata-Version: 2.4
Name: im2deeptrainer
Version: 0.2.2
Summary: Training of new IM2Deep models
Author-email: Robbe Devreese <robbe.devreese@ugent.be>, Robbin Bouwmeester <robbin.bouwmeester@ugent.be>
License:                                  Apache License
Project-URL: GitHub, https://github.com/rodvrees/IM2DeepTrainer
Project-URL: CompOmics, https://www.compomics.com
Keywords: proteomics,peptide,timsTOF,CCS
Classifier: Intended Audience :: Science/Research
Classifier: License :: OSI Approved :: Apache Software License
Classifier: Operating System :: OS Independent
Classifier: Programming Language :: Python :: 3 :: Only
Classifier: Topic :: Scientific/Engineering :: Bio-Informatics
Requires-Python: >=3.10
License-File: LICENSE
Requires-Dist: click
Requires-Dist: scipy
Requires-Dist: wandb
Requires-Dist: matplotlib
Requires-Dist: torch
Requires-Dist: deeplc<4
Requires-Dist: deeplcretrainer
Requires-Dist: lightning==2.2.4
Requires-Dist: pandas
Requires-Dist: numpy
Requires-Dist: rich
Provides-Extra: dev
Requires-Dist: black; extra == "dev"
Requires-Dist: isort>5; extra == "dev"
Requires-Dist: pytest; extra == "dev"
Requires-Dist: pytest-cov; extra == "dev"
Provides-Extra: docs
Requires-Dist: sphinx; extra == "docs"
Requires-Dist: numpydoc<2,>=1; extra == "docs"
Requires-Dist: recommonmark; extra == "docs"
Requires-Dist: sphinx-mdinclude; extra == "docs"
Requires-Dist: toml; extra == "docs"
Requires-Dist: semver>=2; extra == "docs"
Requires-Dist: sphinx_rtd_theme; extra == "docs"
Requires-Dist: sphinx-autobuild; extra == "docs"
Dynamic: license-file
